cocoapodsgraph/__init__.py
cocoapodsgraph/__main__.py
cocoapodsgraph/executor.py
cocoapods_graph-0.1.2.dist-info/LICENSE
cocoapods_graph-0.1.2.dist-info/METADATA
cocoapods_graph-0.1.2.dist-info/WHEEL
cocoapods_graph-0.1.2.dist-info/entry_points.txt
cocoapods_graph-0.1.2.dist-info/top_level.txt
cocoapods_graph-0.1.2.dist-info/RECORD
