Metadata-Version: 2.1
Name: cocoapods-graph
Version: 0.1.2
Summary: Cocoapods dependencies graph generator
Home-page: https://github.com/erickjung/cocoapods-graph
Author: Erick Jung
Author-email: erickjung@gmail.com
Classifier: Programming Language :: Python :: 2
Classifier: License :: OSI Approved :: MIT License
Classifier: Operating System :: MacOS
License-File: LICENSE
